Workbook

Sheet Assumptions
A1: LBO Model — Assumptions
A2: Yellow cells = hardcoded inputs. Change these to drive the whole model.
A4: Transaction
A5: Transaction / Entry Year | B5: 2026
A6: Hold Period (years) | B6: 5
A7: Entry EV / EBITDA Multiple | B7: 9
A8: Exit EV / EBITDA Multiple | B8: 9
A9: Transaction Fees (% of EV) | B9: 0.02
A10: Financing Fees (% of Total Debt) | B10: 0.02
A12: Operating Assumptions (Entry Year, Year 0)
A13: Entry Revenue ($mm) | B13: 500
A14: Revenue Growth Rate (annual) | B14: 0.06
A15: Entry EBITDA Margin | B15: 0.22
A16: EBITDA Margin Expansion (bps/yr) | B16: 0.0025
A17: D&A (% of Revenue) | B17: 0.035
A18: Capex (% of Revenue) | B18: 0.03
A19: Change in NWC (% of Rev. Growth $) | B19: 0.15
A20: Tax Rate | B20: 0.25
A22: Financing Assumptions
A23: Term Loan Leverage (x EBITDA) | B23: 4.5
A24: Term Loan Interest Rate | B24: 0.085
A25: Term Loan Mandatory Amort (%/yr of orig.) | B25: 0.01
A26: Subordinated Notes Leverage (x EBITDA) | B26: 1.5
A27: Subordinated Notes Interest Rate | B27: 0.11
A28: Revolver Interest Rate | B28: 0.075
A29: Minimum Cash Balance ($mm) | B29: 10
A30: Cash Sweep (% of Excess FCF to Debt) | B30: 1
A31: Management Rollover (% of Sponsor Equity) | B31: 0

Sheet Sources & Uses
A1: Sources & Uses
A3: Entry EBITDA ($mm) | B3: =Assumptions!$B$13*Assumptions!$B$15 -> 110
A5: Uses
A6: Purchase Enterprise Value | B6: =B3*Assumptions!$B$7 -> 990
A7: Transaction Fees | B7: =B6*Assumptions!$B$9 -> 19.8
A8: Financing Fees | B8: =B15*Assumptions!$B$10 -> 13.2
A9: Total Uses | B9: =SUM(B6:B8) -> 1023
A11: Sources
A12: Term Loan | B12: =B3*Assumptions!$B$23 -> 495
A13: Subordinated Notes | B13: =B3*Assumptions!$B$26 -> 165
A14: Revolver Draw at Close | B14: 0
A15: Total Debt | B15: =SUM(B12:B14) -> 660
A16: Management Rollover Equity | B16: =(B9-B15)*Assumptions!$B$31 -> 0
A17: Sponsor Equity (plug) | B17: =B9-B15-B16 -> 363
A18: Total Sources | B18: =B15+B16+B17 -> 1023
A19: Check (Sources - Uses) | B19: =B18-B9 -> 0
A21: Opening Leverage (Total Debt / EBITDA) | B21: =B15/B3 -> 6

Sheet Operating Model
A1: Operating Model
A3: Year | B3: =Assumptions!$B$5 -> 2026 | C3: =B3+1 -> 2027 | D3: =C3+1 -> 2028 | E3: =D3+1 -> 2029 | F3: =E3+1 -> 2030 | G3: =F3+1 -> 2031
A4: Revenue | B4: =Assumptions!$B$13 -> 500 | C4: =B4*(1+Assumptions!$B$14) -> 530 | D4: =C4*(1+Assumptions!$B$14) -> 561.8 | E4: =D4*(1+Assumptions!$B$14) -> 595.508 | F4: =E4*(1+Assumptions!$B$14) -> 631.23848 | G4: =F4*(1+Assumptions!$B$14) -> 669.11279
A5: % growth | C5: =C4/B4-1 -> 0.06 | D5: =D4/C4-1 -> 0.06 | E5: =E4/D4-1 -> 0.06 | F5: =F4/E4-1 -> 0.06 | G5: =G4/F4-1 -> 0.06
A6: EBITDA Margin | B6: =Assumptions!$B$15 -> 0.22 | C6: =B6+Assumptions!$B$16 -> 0.2225 | D6: =C6+Assumptions!$B$16 -> 0.225 | E6: =D6+Assumptions!$B$16 -> 0.2275 | F6: =E6+Assumptions!$B$16 -> 0.23 | G6: =F6+Assumptions!$B$16 -> 0.2325
A7: EBITDA | B7: =B4*B6 -> 110 | C7: =C4*C6 -> 117.925 | D7: =D4*D6 -> 126.405 | E7: =E4*E6 -> 135.47807 | F7: =F4*F6 -> 145.18485 | G7: =G4*G6 -> 155.56872
A8: Less: D&A | B8: =-B4*Assumptions!$B$17 -> -17.5 | C8: =-C4*Assumptions!$B$17 -> -18.55 | D8: =-D4*Assumptions!$B$17 -> -19.663 | E8: =-E4*Assumptions!$B$17 -> -20.84278 | F8: =-F4*Assumptions!$B$17 -> -22.093347 | G8: =-G4*Assumptions!$B$17 -> -23.418948
A9: EBIT | B9: =B7+B8 -> 92.5 | C9: =C7+C8 -> 99.375 | D9: =D7+D8 -> 106.742 | E9: =E7+E8 -> 114.63529 | F9: =F7+F8 -> 123.0915 | G9: =G7+G8 -> 132.14978
A10: Less: Cash Interest Expense, net | B10: 0 | C10: =-'Debt Schedule'!C28 -> -60.225 | D10: =-'Debt Schedule'!D28 -> -57.886437 | E10: =-'Debt Schedule'!E28 -> -54.93858 | F10: =-'Debt Schedule'!F28 -> -51.309601 | G10: =-'Debt Schedule'!G28 -> -46.920792
A11: EBT | B11: =B9+B10 -> 92.5 | C11: =C9+C10 -> 39.15 | D11: =D9+D10 -> 48.855563 | E11: =E9+E10 -> 59.69671 | F11: =F9+F10 -> 71.781902 | G11: =G9+G10 -> 85.228984
A12: Less: Cash Taxes | B12: =-MAX(B11,0)*Assumptions!$B$20 -> -23.125 | C12: =-MAX(C11,0)*Assumptions!$B$20 -> -9.7875 | D12: =-MAX(D11,0)*Assumptions!$B$20 -> -12.213891 | E12: =-MAX(E11,0)*Assumptions!$B$20 -> -14.924177 | F12: =-MAX(F11,0)*Assumptions!$B$20 -> -17.945476 | G12: =-MAX(G11,0)*Assumptions!$B$20 -> -21.307246
A13: Net Income | B13: =B11+B12 -> 69.375 | C13: =C11+C12 -> 29.3625 | D13: =D11+D12 -> 36.641672 | E13: =E11+E12 -> 44.772532 | F13: =F11+F12 -> 53.836427 | G13: =G11+G12 -> 63.921738

Sheet Free Cash Flow
A1: Free Cash Flow
A3: Year | B3: ='Operating Model'!B3 -> 2026 | C3: ='Operating Model'!C3 -> 2027 | D3: ='Operating Model'!D3 -> 2028 | E3: ='Operating Model'!E3 -> 2029 | F3: ='Operating Model'!F3 -> 2030 | G3: ='Operating Model'!G3 -> 2031
A4: Net Income | B4: 0 | C4: ='Operating Model'!C13 -> 29.3625 | D4: ='Operating Model'!D13 -> 36.641672 | E4: ='Operating Model'!E13 -> 44.772532 | F4: ='Operating Model'!F13 -> 53.836427 | G4: ='Operating Model'!G13 -> 63.921738
A5: Plus: D&A | B5: 0 | C5: =-'Operating Model'!C8 -> 18.55 | D5: =-'Operating Model'!D8 -> 19.663 | E5: =-'Operating Model'!E8 -> 20.84278 | F5: =-'Operating Model'!F8 -> 22.093347 | G5: =-'Operating Model'!G8 -> 23.418948
A6: Less: Capex | B6: 0 | C6: =-'Operating Model'!C4*Assumptions!$B$18 -> -15.9 | D6: =-'Operating Model'!D4*Assumptions!$B$18 -> -16.854 | E6: =-'Operating Model'!E4*Assumptions!$B$18 -> -17.86524 | F6: =-'Operating Model'!F4*Assumptions!$B$18 -> -18.937154 | G6: =-'Operating Model'!G4*Assumptions!$B$18 -> -20.073384
A7: Less: Increase in NWC | B7: 0 | C7: =-('Operating Model'!C4-'Operating Model'!B4)*Assumptions!$B$19 -> -4.5 | D7: =-('Operating Model'!D4-'Operating Model'!C4)*Assumptions!$B$19 -> -4.77 | E7: =-('Operating Model'!E4-'Operating Model'!D4)*Assumptions!$B$19 -> -5.0562 | F7: =-('Operating Model'!F4-'Operating Model'!E4)*Assumptions!$B$19 -> -5.359572 | G7: =-('Operating Model'!G4-'Operating Model'!F4)*Assumptions!$B$19 -> -5.6811463
A8: Cash Flow Available for Debt Service (CFADS) | B8: =B4+B5+B6+B7 -> 0 | C8: =C4+C5+C6+C7 -> 27.5125 | D8: =D4+D5+D6+D7 -> 34.680672 | E8: =E4+E5+E6+E7 -> 42.693872 | F8: =F4+F5+F6+F7 -> 51.633047 | G8: =G4+G5+G6+G7 -> 61.586155

Sheet Debt Schedule
A1: Debt Schedule
A3: Year | B3: ='Operating Model'!B3 -> 2026 | C3: ='Operating Model'!C3 -> 2027 | D3: ='Operating Model'!D3 -> 2028 | E3: ='Operating Model'!E3 -> 2029 | F3: ='Operating Model'!F3 -> 2030 | G3: ='Operating Model'!G3 -> 2031
A5: CFADS (from FCF tab) | B5: 0 | C5: ='Free Cash Flow'!C8 -> 27.5125 | D5: ='Free Cash Flow'!D8 -> 34.680672 | E5: ='Free Cash Flow'!E8 -> 42.693872 | F5: ='Free Cash Flow'!F8 -> 51.633047 | G5: ='Free Cash Flow'!G8 -> 61.586155
A6: Less: Mandatory Term Loan Amort. | B6: 0 | C6: =C11 -> -4.95 | D6: =D11 -> -4.95 | E6: =E11 -> -4.95 | F6: =F11 -> -4.95 | G6: =G11 -> -4.95
A7: Cash Flow Available for Optional Sweep | B7: 0 | C7: =MAX(C5+C6,0)*Assumptions!$B$30 -> 22.5625 | D7: =MAX(D5+D6,0)*Assumptions!$B$30 -> 29.730672 | E7: =MAX(E5+E6,0)*Assumptions!$B$30 -> 37.743872 | F7: =MAX(F5+F6,0)*Assumptions!$B$30 -> 46.683047 | G7: =MAX(G5+G6,0)*Assumptions!$B$30 -> 56.636155
A9: Term Loan
A10: Beginning Balance | B10: 0 | C10: =B13 -> 495 | D10: =C13 -> 467.4875 | E10: =D13 -> 432.80683 | F10: =E13 -> 390.11296 | G10: =F13 -> 338.47991
A11: Mandatory Amortization | B11: 0 | C11: =-MIN('Sources & Uses'!$B$12*Assumptions!$B$25,C10) -> -4.95 | D11: =-MIN('Sources & Uses'!$B$12*Assumptions!$B$25,D10) -> -4.95 | E11: =-MIN('Sources & Uses'!$B$12*Assumptions!$B$25,E10) -> -4.95 | F11: =-MIN('Sources & Uses'!$B$12*Assumptions!$B$25,F10) -> -4.95 | G11: =-MIN('Sources & Uses'!$B$12*Assumptions!$B$25,G10) -> -4.95
A12: Optional Sweep | B12: 0 | C12: =-MIN(MAX(C7,0),C10+C11) -> -22.5625 | D12: =-MIN(MAX(D7,0),D10+D11) -> -29.730672 | E12: =-MIN(MAX(E7,0),E10+E11) -> -37.743872 | F12: =-MIN(MAX(F7,0),F10+F11) -> -46.683047 | G12: =-MIN(MAX(G7,0),G10+G11) -> -56.636155
A13: Ending Balance | B13: ='Sources & Uses'!$B$12 -> 495 | C13: =C10+C11+C12 -> 467.4875 | D13: =D10+D11+D12 -> 432.80683 | E13: =E10+E11+E12 -> 390.11296 | F13: =F10+F11+F12 -> 338.47991 | G13: =G10+G11+G12 -> 276.89375
A14: Interest Expense (on beg. balance) | B14: 0 | C14: =C10*Assumptions!$B$24 -> 42.075 | D14: =D10*Assumptions!$B$24 -> 39.736438 | E14: =E10*Assumptions!$B$24 -> 36.78858 | F14: =F10*Assumptions!$B$24 -> 33.159601 | G14: =G10*Assumptions!$B$24 -> 28.770792
A16: Subordinated Notes
A17: Beginning Balance | B17: 0 | C17: =B19 -> 165 | D17: =C19 -> 165 | E17: =D19 -> 165 | F17: =E19 -> 165 | G17: =F19 -> 165
A18: Optional Sweep (after Term Loan repaid) | B18: 0 | C18: =-MIN(MAX(C7+C12,0),C17) -> 0 | D18: =-MIN(MAX(D7+D12,0),D17) -> 0 | E18: =-MIN(MAX(E7+E12,0),E17) -> 0 | F18: =-MIN(MAX(F7+F12,0),F17) -> 0 | G18: =-MIN(MAX(G7+G12,0),G17) -> 0
A19: Ending Balance | B19: ='Sources & Uses'!$B$13 -> 165 | C19: =C17+C18 -> 165 | D19: =D17+D18 -> 165 | E19: =E17+E18 -> 165 | F19: =F17+F18 -> 165 | G19: =G17+G18 -> 165
A20: Interest Expense (on beg. balance) | B20: 0 | C20: =C17*Assumptions!$B$27 -> 18.15 | D20: =D17*Assumptions!$B$27 -> 18.15 | E20: =E17*Assumptions!$B$27 -> 18.15 | F20: =F17*Assumptions!$B$27 -> 18.15 | G20: =G17*Assumptions!$B$27 -> 18.15
A22: Revolver
A23: Beginning Balance | B23: 0 | C23: =B25 -> 0 | D23: =C25 -> 0 | E23: =D25 -> 0 | F23: =E25 -> 0 | G23: =F25 -> 0
A24: (Draw) / Paydown | B24: ='Sources & Uses'!$B$14 -> 0 | C24: =-(MIN(C5+C6+C12+C18,0)) -> 0 | D24: =-(MIN(D5+D6+D12+D18,0)) -> 0 | E24: =-(MIN(E5+E6+E12+E18,0)) -> 0 | F24: =-(MIN(F5+F6+F12+F18,0)) -> 0 | G24: =-(MIN(G5+G6+G12+G18,0)) -> 0
A25: Ending Balance | B25: =B23+B24 -> 0 | C25: =MAX(C23+C24,0) -> 0 | D25: =MAX(D23+D24,0) -> 0 | E25: =MAX(E23+E24,0) -> 0 | F25: =MAX(F23+F24,0) -> 0 | G25: =MAX(G23+G24,0) -> 0
A26: Interest Expense (on beg. balance) | B26: 0 | C26: =C23*Assumptions!$B$28 -> 0 | D26: =D23*Assumptions!$B$28 -> 0 | E26: =E23*Assumptions!$B$28 -> 0 | F26: =F23*Assumptions!$B$28 -> 0 | G26: =G23*Assumptions!$B$28 -> 0
A28: Total Interest Expense | B28: =B14+B20+B26 -> 0 | C28: =C14+C20+C26 -> 60.225 | D28: =D14+D20+D26 -> 57.886437 | E28: =E14+E20+E26 -> 54.93858 | F28: =F14+F20+F26 -> 51.309601 | G28: =G14+G20+G26 -> 46.920792
A29: Total Debt (Ending) | B29: =B13+B19+B25 -> 660 | C29: =C13+C19+C25 -> 632.4875 | D29: =D13+D19+D25 -> 597.80683 | E29: =E13+E19+E25 -> 555.11296 | F29: =F13+F19+F25 -> 503.47991 | G29: =G13+G19+G25 -> 441.89375
A30: Cash Balance | B30: =Assumptions!$B$29 -> 10 | C30: =B30+MAX(C5+C6+C12+C18,0)*(1-Assumptions!$B$30) -> 10 | D30: =C30+MAX(D5+D6+D12+D18,0)*(1-Assumptions!$B$30) -> 10 | E30: =D30+MAX(E5+E6+E12+E18,0)*(1-Assumptions!$B$30) -> 10 | F30: =E30+MAX(F5+F6+F12+F18,0)*(1-Assumptions!$B$30) -> 10 | G30: =F30+MAX(G5+G6+G12+G18,0)*(1-Assumptions!$B$30) -> 10
A31: Net Debt | B31: =B29-B30 -> 650 | C31: =C29-C30 -> 622.4875 | D31: =D29-D30 -> 587.80683 | E31: =E29-E30 -> 545.11296 | F31: =F29-F30 -> 493.47991 | G31: =G29-G30 -> 431.89375
A32: Leverage (Net Debt / EBITDA) | B32: =B31/'Operating Model'!B7 -> 5.9090909 | C32: =C31/'Operating Model'!C7 -> 5.2786729 | D32: =D31/'Operating Model'!D7 -> 4.6501865 | E32: =E31/'Operating Model'!E7 -> 4.023625 | F32: =F31/'Operating Model'!F7 -> 3.3989766 | G32: =G31/'Operating Model'!G7 -> 2.7762248

Sheet Returns
A1: Returns Analysis
A3: Exit Year | B3: ='Operating Model'!G3 -> 2031
A4: Exit EBITDA | B4: ='Operating Model'!G7 -> 155.56872
A5: Exit EV/EBITDA Multiple | B5: =Assumptions!$B$8 -> 9
A6: Exit Enterprise Value | B6: =B4*Assumptions!$B$8 -> 1400.1185
A7: Less: Net Debt at Exit | B7: =-'Debt Schedule'!G31 -> -431.89375
A8: Exit Equity Value | B8: =B6+B7 -> 968.22476
A10: Sponsor Returns
A11: Initial Sponsor Equity | B11: ='Sources & Uses'!$B$17 -> 363
A12: Exit Sponsor Equity Proceeds | B12: =B8*(1-Assumptions!$B$31) -> 968.22476
A13: Hold Period (years) | B13: =Assumptions!$B$6 -> 5
A14: MOIC | B14: =B12/B11 -> 2.6672858
A15: IRR | B15: =(B14)^(1/B13)-1 -> 0.21678518
A17: Cash Flow Check (for XIRR)
A18: Year 0 (Equity Out) | B18: =-B11 -> -363
A19: Years 1-4 | B19: 0
A20: Exit Year (Equity In) | B20: =B12 -> 968.22476
A22: Note: exit assumed at end of Year 5 (col G). Change FORECAST_YEARS in the script if you want a different hold length.

Sheet Sensitivity
A1: Sensitivity Analysis
A2: Holds leverage, growth, margins, and rates fixed at their Assumptions-tab values; varies only Entry and Exit EV/EBITDA multiples.
A4: MOIC — Entry Multiple (rows) vs Exit Multiple (columns)
B5: MOIC | C5: =Assumptions!$B$8-1 -> 8 | D5: =Assumptions!$B$8-0.5 -> 8.5 | E5: =Assumptions!$B$8 -> 9 | F5: =Assumptions!$B$8+0.5 -> 9.5 | G5: =Assumptions!$B$8+1 -> 10
B6: =Assumptions!$B$7-1 -> 8 | C6: =('Operating Model'!G7*C$5-'Debt Schedule'!G31)/(('Sources & Uses'!$B$3*$B6*(1+Assumptions!$B$9)+'Sources & Uses'!$B$15*Assumptions!$B$10)-'Sources & Uses'!$B$15) -> 3.2402553 | D6: =('Operating Model'!G7*D$5-'Debt Schedule'!G31)/(('Sources & Uses'!$B$3*$B6*(1+Assumptions!$B$9)+'Sources & Uses'!$B$15*Assumptions!$B$10)-'Sources & Uses'!$B$15) -> 3.5504003 | E6: =('Operating Model'!G7*E$5-'Debt Schedule'!G31)/(('Sources & Uses'!$B$3*$B6*(1+Assumptions!$B$9)+'Sources & Uses'!$B$15*Assumptions!$B$10)-'Sources & Uses'!$B$15) -> 3.8605453 | F6: =('Operating Model'!G7*F$5-'Debt Schedule'!G31)/(('Sources & Uses'!$B$3*$B6*(1+Assumptions!$B$9)+'Sources & Uses'!$B$15*Assumptions!$B$10)-'Sources & Uses'!$B$15) -> 4.1706903 | G6: =('Operating Model'!G7*G$5-'Debt Schedule'!G31)/(('Sources & Uses'!$B$3*$B6*(1+Assumptions!$B$9)+'Sources & Uses'!$B$15*Assumptions!$B$10)-'Sources & Uses'!$B$15) -> 4.4808352
B7: =Assumptions!$B$7-0.5 -> 8.5 | C7: =('Operating Model'!G7*C$5-'Debt Schedule'!G31)/(('Sources & Uses'!$B$3*$B7*(1+Assumptions!$B$9)+'Sources & Uses'!$B$15*Assumptions!$B$10)-'Sources & Uses'!$B$15) -> 2.6479506 | D7: =('Operating Model'!G7*D$5-'Debt Schedule'!G31)/(('Sources & Uses'!$B$3*$B7*(1+Assumptions!$B$9)+'Sources & Uses'!$B$15*Assumptions!$B$10)-'Sources & Uses'!$B$15) -> 2.9014024 | E7: =('Operating Model'!G7*E$5-'Debt Schedule'!G31)/(('Sources & Uses'!$B$3*$B7*(1+Assumptions!$B$9)+'Sources & Uses'!$B$15*Assumptions!$B$10)-'Sources & Uses'!$B$15) -> 3.1548542 | F7: =('Operating Model'!G7*F$5-'Debt Schedule'!G31)/(('Sources & Uses'!$B$3*$B7*(1+Assumptions!$B$9)+'Sources & Uses'!$B$15*Assumptions!$B$10)-'Sources & Uses'!$B$15) -> 3.408306 | G7: =('Operating Model'!G7*G$5-'Debt Schedule'!G31)/(('Sources & Uses'!$B$3*$B7*(1+Assumptions!$B$9)+'Sources & Uses'!$B$15*Assumptions!$B$10)-'Sources & Uses'!$B$15) -> 3.6617578
B8: =Assumptions!$B$7 -> 9 | C8: =('Operating Model'!G7*C$5-'Debt Schedule'!G31)/(('Sources & Uses'!$B$3*$B8*(1+Assumptions!$B$9)+'Sources & Uses'!$B$15*Assumptions!$B$10)-'Sources & Uses'!$B$15) -> 2.2387219 | D8: =('Operating Model'!G7*D$5-'Debt Schedule'!G31)/(('Sources & Uses'!$B$3*$B8*(1+Assumptions!$B$9)+'Sources & Uses'!$B$15*Assumptions!$B$10)-'Sources & Uses'!$B$15) -> 2.4530038 | E8: =('Operating Model'!G7*E$5-'Debt Schedule'!G31)/(('Sources & Uses'!$B$3*$B8*(1+Assumptions!$B$9)+'Sources & Uses'!$B$15*Assumptions!$B$10)-'Sources & Uses'!$B$15) -> 2.6672858 | F8: =('Operating Model'!G7*F$5-'Debt Schedule'!G31)/(('Sources & Uses'!$B$3*$B8*(1+Assumptions!$B$9)+'Sources & Uses'!$B$15*Assumptions!$B$10)-'Sources & Uses'!$B$15) -> 2.8815678 | G8: =('Operating Model'!G7*G$5-'Debt Schedule'!G31)/(('Sources & Uses'!$B$3*$B8*(1+Assumptions!$B$9)+'Sources & Uses'!$B$15*Assumptions!$B$10)-'Sources & Uses'!$B$15) -> 3.0958498
B9: =Assumptions!$B$7+0.5 -> 9.5 | C9: =('Operating Model'!G7*C$5-'Debt Schedule'!G31)/(('Sources & Uses'!$B$3*$B9*(1+Assumptions!$B$9)+'Sources & Uses'!$B$15*Assumptions!$B$10)-'Sources & Uses'!$B$15) -> 1.9390504 | D9: =('Operating Model'!G7*D$5-'Debt Schedule'!G31)/(('Sources & Uses'!$B$3*$B9*(1+Assumptions!$B$9)+'Sources & Uses'!$B$15*Assumptions!$B$10)-'Sources & Uses'!$B$15) -> 2.124649 | E9: =('Operating Model'!G7*E$5-'Debt Schedule'!G31)/(('Sources & Uses'!$B$3*$B9*(1+Assumptions!$B$9)+'Sources & Uses'!$B$15*Assumptions!$B$10)-'Sources & Uses'!$B$15) -> 2.3102476 | F9: =('Operating Model'!G7*F$5-'Debt Schedule'!G31)/(('Sources & Uses'!$B$3*$B9*(1+Assumptions!$B$9)+'Sources & Uses'!$B$15*Assumptions!$B$10)-'Sources & Uses'!$B$15) -> 2.4958461 | G9: =('Operating Model'!G7*G$5-'Debt Schedule'!G31)/(('Sources & Uses'!$B$3*$B9*(1+Assumptions!$B$9)+'Sources & Uses'!$B$15*Assumptions!$B$10)-'Sources & Uses'!$B$15) -> 2.6814447
B10: =Assumptions!$B$7+1 -> 10 | C10: =('Operating Model'!G7*C$5-'Debt Schedule'!G31)/(('Sources & Uses'!$B$3*$B10*(1+Assumptions!$B$9)+'Sources & Uses'!$B$15*Assumptions!$B$10)-'Sources & Uses'!$B$15) -> 1.7101348 | D10: =('Operating Model'!G7*D$5-'Debt Schedule'!G31)/(('Sources & Uses'!$B$3*$B10*(1+Assumptions!$B$9)+'Sources & Uses'!$B$15*Assumptions!$B$10)-'Sources & Uses'!$B$15) -> 1.8738224 | E10: =('Operating Model'!G7*E$5-'Debt Schedule'!G31)/(('Sources & Uses'!$B$3*$B10*(1+Assumptions!$B$9)+'Sources & Uses'!$B$15*Assumptions!$B$10)-'Sources & Uses'!$B$15) -> 2.03751 | F10: =('Operating Model'!G7*F$5-'Debt Schedule'!G31)/(('Sources & Uses'!$B$3*$B10*(1+Assumptions!$B$9)+'Sources & Uses'!$B$15*Assumptions!$B$10)-'Sources & Uses'!$B$15) -> 2.2011976 | G10: =('Operating Model'!G7*G$5-'Debt Schedule'!G31)/(('Sources & Uses'!$B$3*$B10*(1+Assumptions!$B$9)+'Sources & Uses'!$B$15*Assumptions!$B$10)-'Sources & Uses'!$B$15) -> 2.3648853
A13: IRR — Entry Multiple (rows) vs Exit Multiple (columns)
B14: IRR | C14: =Assumptions!$B$8-1 -> 8 | D14: =Assumptions!$B$8-0.5 -> 8.5 | E14: =Assumptions!$B$8 -> 9 | F14: =Assumptions!$B$8+0.5 -> 9.5 | G14: =Assumptions!$B$8+1 -> 10
B15: =Assumptions!$B$7-1 -> 8 | C15: =(C6)^(1/Assumptions!$B$6)-1 -> 0.26507376 | D15: =(D6)^(1/Assumptions!$B$6)-1 -> 0.28841409 | E15: =(E6)^(1/Assumptions!$B$6)-1 -> 0.31017627 | F15: =(F6)^(1/Assumptions!$B$6)-1 -> 0.33058183 | G15: =(G6)^(1/Assumptions!$B$6)-1 -> 0.34980737
B16: =Assumptions!$B$7-0.5 -> 8.5 | C16: =(C7)^(1/Assumptions!$B$6)-1 -> 0.21501594 | D16: =(D7)^(1/Assumptions!$B$6)-1 -> 0.23743271 | E16: =(E7)^(1/Assumptions!$B$6)-1 -> 0.25833379 | F16: =(F7)^(1/Assumptions!$B$6)-1 -> 0.27793192 | G16: =(G7)^(1/Assumptions!$B$6)-1 -> 0.29639672
B17: =Assumptions!$B$7 -> 9 | C17: =(C8)^(1/Assumptions!$B$6)-1 -> 0.17489763 | D17: =(D8)^(1/Assumptions!$B$6)-1 -> 0.19657423 | E17: =(E8)^(1/Assumptions!$B$6)-1 -> 0.21678518 | F17: =(F8)^(1/Assumptions!$B$6)-1 -> 0.2357362 | G17: =(G8)^(1/Assumptions!$B$6)-1 -> 0.25359132
B18: =Assumptions!$B$7+0.5 -> 9.5 | C18: =(C9)^(1/Assumptions!$B$6)-1 -> 0.14161015 | D18: =(D9)^(1/Assumptions!$B$6)-1 -> 0.1626726 | E18: =(E9)^(1/Assumptions!$B$6)-1 -> 0.18231093 | F18: =(F9)^(1/Assumptions!$B$6)-1 -> 0.20072502 | G18: =(G9)^(1/Assumptions!$B$6)-1 -> 0.21807427
B19: =Assumptions!$B$7+1 -> 10 | C19: =(C10)^(1/Assumptions!$B$6)-1 -> 0.11328425 | D19: =(D10)^(1/Assumptions!$B$6)-1 -> 0.1338241 | E19: =(E10)^(1/Assumptions!$B$6)-1 -> 0.15297516 | F19: =(F10)^(1/Assumptions!$B$6)-1 -> 0.17093236 | G19: =(G10)^(1/Assumptions!$B$6)-1 -> 0.18785113
