Workbook

Sheet Summary
B1: DEAL SUMMARY
B3: Deal Name | C3: =Assumptions!C3 -> Project Falcon
B4: Borrower | C4: =Assumptions!C4 -> Sample Borrower LLC
B5: Close Date | C5: =Assumptions!C5 -> 2026-01-01
B6: Maturity (Years) | C6: =Assumptions!C6 -> 5
B7: Total Commitment ($mm) | C7: =Assumptions!C25 -> 100
B8: Total Leverage at Close (x) | C8: =Assumptions!C26 -> 2
B9: Assumed Exit Year | C9: =Assumptions!C34 -> 3
B11: Tranche A IRR | C11: =Returns!B27 -> 0.10994733
B12: Tranche A MOIC | C12: =Returns!B30 -> 1.1655138
B13: Tranche B IRR | C13: =Returns!B28 -> 0.13708904
B14: Tranche B MOIC | C14: =Returns!B31 -> 1.3937976
B15: Blended IRR | C15: =Returns!B29 -> 0.12467577
B16: Blended MOIC | C16: =Returns!B32 -> 1.2562716
B18: Covenant Test Result | C18: =IF(COUNTIF(Covenants!L4:L23,"Fail")>0,"BREACH DETECTED","All Tests Pass") -> All Tests Pass

Sheet Assumptions
B1: PRIVATE CREDIT MODEL — ASSUMPTIONS
B3: Deal Name | C3: Project Falcon
B4: Borrower | C4: Sample Borrower LLC
B5: Close Date | C5: 2026-01-01
B6: Maturity (Years) | C6: 5
B7: EBITDA at Close ($mm) | C7: 50
B8: EBITDA Annual Growth (%) | C8: 0.05
B10: TRANCHE A — FIRST OUT
B11: Principal ($mm) | C11: 60
B12: Spread (bps over SOFR) | C12: 550
B13: SOFR Floor (%) | C13: 0.01
B14: OID (% of Par Funded) | C14: 0.99
B15: Annual Mandatory Amortization (%) | C15: 0.01
B17: TRANCHE B — LAST OUT
B18: Principal ($mm) | C18: 40
B19: Spread (bps over SOFR) | C19: 800
B20: SOFR Floor (%) | C20: 0.01
B21: OID (% of Par Funded) | C21: 0.98
B22: Annual Mandatory Amortization (%) | C22: 0
B24: TOTALS
B25: Total Commitment ($mm) | C25: =C11+C18 -> 100
B26: Total Leverage at Close (x) | C26: =C25/C7 -> 2
B28: COVENANTS
B29: Max Total Leverage — Years 1-2 (x) | C29: 6.5
B30: Max Total Leverage — Years 3+ (x) | C30: 6
B31: Min Interest Coverage Ratio (x) | C31: 2
B33: EXIT ASSUMPTION
B34: Assumed Exit Year | C34: 3
B35: Exit Period (Quarter #) | C35: =C34*4 -> 12
B37: CALL PROTECTION SCHEDULE
C38: Year | D38: Call Premium
C39: 1 | D39: 1.02
C40: 2 | D40: 1.01
C41: 3 | D41: 1
C42: 4 | D42: 1
C43: 5 | D43: 1
B45: Applicable Call Premium | C45: =VLOOKUP(C34,C39:D43,2,FALSE) -> 1
B47: CASH SWEEP
B48: FCF Conversion (% of EBITDA) | C48: 0.7
B49: Cash Sweep (% of Excess Cash Flow) | C49: 0.75

Sheet SOFR Curve
B1: SOFR FORWARD CURVE (EDITABLE)
A3: Period | B3: Date | C3: SOFR Forward Rate (%)
A4: 1 | B4: =EDATE(Assumptions!$C$5,1*3) -> 46113 | C4: 0.045
A5: 2 | B5: =EDATE(Assumptions!$C$5,2*3) -> 46204 | C5: 0.0445
A6: 3 | B6: =EDATE(Assumptions!$C$5,3*3) -> 46296 | C6: 0.044
A7: 4 | B7: =EDATE(Assumptions!$C$5,4*3) -> 46388 | C7: 0.0435
A8: 5 | B8: =EDATE(Assumptions!$C$5,5*3) -> 46478 | C8: 0.043
A9: 6 | B9: =EDATE(Assumptions!$C$5,6*3) -> 46569 | C9: 0.0425
A10: 7 | B10: =EDATE(Assumptions!$C$5,7*3) -> 46661 | C10: 0.042
A11: 8 | B11: =EDATE(Assumptions!$C$5,8*3) -> 46753 | C11: 0.0415
A12: 9 | B12: =EDATE(Assumptions!$C$5,9*3) -> 46844 | C12: 0.041
A13: 10 | B13: =EDATE(Assumptions!$C$5,10*3) -> 46935 | C13: 0.0405
A14: 11 | B14: =EDATE(Assumptions!$C$5,11*3) -> 47027 | C14: 0.04
A15: 12 | B15: =EDATE(Assumptions!$C$5,12*3) -> 47119 | C15: 0.0395
A16: 13 | B16: =EDATE(Assumptions!$C$5,13*3) -> 47209 | C16: 0.039
A17: 14 | B17: =EDATE(Assumptions!$C$5,14*3) -> 47300 | C17: 0.0385
A18: 15 | B18: =EDATE(Assumptions!$C$5,15*3) -> 47392 | C18: 0.038
A19: 16 | B19: =EDATE(Assumptions!$C$5,16*3) -> 47484 | C19: 0.0375
A20: 17 | B20: =EDATE(Assumptions!$C$5,17*3) -> 47574 | C20: 0.037
A21: 18 | B21: =EDATE(Assumptions!$C$5,18*3) -> 47665 | C21: 0.0365
A22: 19 | B22: =EDATE(Assumptions!$C$5,19*3) -> 47757 | C22: 0.036
A23: 20 | B23: =EDATE(Assumptions!$C$5,20*3) -> 47849 | C23: 0.0355

Sheet Debt Schedule
B1: QUARTERLY DEBT SCHEDULE
A3: Period | B3: Date | C3: SOFR Rate | D3: Beg Bal A | E3: All-in Rate A | F3: Cash Int A | G3: Sched Amort A | H3: End Bal A | I3: Beg Bal B | J3: All-in Rate B | K3: Cash Int B | L3: Sched Amort B | M3: End Bal B | N3: Total Beg Bal | O3: Total Cash Int | P3: Total Amort | Q3: Total End Bal | R3: Qtrly EBITDA | S3: ECF Avail. for Sweep | T3: Cash Sweep A | U3: Cash Sweep B | V3: Total Cash Sweep
A4: 1 | B4: ='SOFR Curve'!B4 -> 46113 | C4: ='SOFR Curve'!C4 -> 0.045 | D4: =Assumptions!$C$11 -> 60 | E4: =MAX(C4,Assumptions!$C$13)+Assumptions!$C$12/10000 -> 0.1 | F4: =D4*E4/4 -> 1.5 | G4: =MIN(D4,Assumptions!$C$11*Assumptions!$C$15/4) -> 0.15 | H4: =D4-G4-T4 -> 55.381963 | I4: =Assumptions!$C$18 -> 40 | J4: =MAX(C4,Assumptions!$C$20)+Assumptions!$C$19/10000 -> 0.125 | K4: =I4*J4/4 -> 1.25 | L4: =MIN(I4,Assumptions!$C$18*Assumptions!$C$22/4) -> 0 | M4: =I4-L4-U4 -> 40 | N4: =D4+I4 -> 100 | O4: =F4+K4 -> 2.75 | P4: =G4+L4 -> 0.15 | Q4: =H4+M4 -> 95.381963 | R4: =Assumptions!$C$7*(1+Assumptions!$C$8)^(A4/4)/4 -> 12.653403 | S4: =MAX(0,R4*Assumptions!$C$48-O4-P4)*Assumptions!$C$49 -> 4.4680365 | T4: =MIN(D4-G4,S4) -> 4.4680365 | U4: =MIN(I4-L4,MAX(0,S4-T4)) -> 0 | V4: =T4+U4 -> 4.4680365
A5: 2 | B5: ='SOFR Curve'!B5 -> 46204 | C5: ='SOFR Curve'!C5 -> 0.0445 | D5: =H4 -> 55.381963 | E5: =MAX(C5,Assumptions!$C$13)+Assumptions!$C$12/10000 -> 0.0995 | F5: =D5*E5/4 -> 1.3776263 | G5: =MIN(D5,Assumptions!$C$11*Assumptions!$C$15/4) -> 0.15 | H5: =D5-G5-T5 -> 50.586872 | I5: =M4 -> 40 | J5: =MAX(C5,Assumptions!$C$20)+Assumptions!$C$19/10000 -> 0.1245 | K5: =I5*J5/4 -> 1.245 | L5: =MIN(I5,Assumptions!$C$18*Assumptions!$C$22/4) -> 0 | M5: =I5-L5-U5 -> 40 | N5: =D5+I5 -> 95.381963 | O5: =F5+K5 -> 2.6226263 | P5: =G5+L5 -> 0.15 | Q5: =H5+M5 -> 90.586872 | R5: =Assumptions!$C$7*(1+Assumptions!$C$8)^(A5/4)/4 -> 12.808688 | S5: =MAX(0,R5*Assumptions!$C$48-O5-P5)*Assumptions!$C$49 -> 4.6450917 | T5: =MIN(D5-G5,S5) -> 4.6450917 | U5: =MIN(I5-L5,MAX(0,S5-T5)) -> 0 | V5: =T5+U5 -> 4.6450917
A6: 3 | B6: ='SOFR Curve'!B6 -> 46296 | C6: ='SOFR Curve'!C6 -> 0.044 | D6: =H5 -> 50.586872 | E6: =MAX(C6,Assumptions!$C$13)+Assumptions!$C$12/10000 -> 0.099 | F6: =D6*E6/4 -> 1.2520251 | G6: =MIN(D6,Assumptions!$C$11*Assumptions!$C$15/4) -> 0.15 | H6: =D6-G6-T6 -> 45.611304 | I6: =M5 -> 40 | J6: =MAX(C6,Assumptions!$C$20)+Assumptions!$C$19/10000 -> 0.124 | K6: =I6*J6/4 -> 1.24 | L6: =MIN(I6,Assumptions!$C$18*Assumptions!$C$22/4) -> 0 | M6: =I6-L6-U6 -> 40 | N6: =D6+I6 -> 90.586872 | O6: =F6+K6 -> 2.4920251 | P6: =G6+L6 -> 0.15 | Q6: =H6+M6 -> 85.611304 | R6: =Assumptions!$C$7*(1+Assumptions!$C$8)^(A6/4)/4 -> 12.96588 | S6: =MAX(0,R6*Assumptions!$C$48-O6-P6)*Assumptions!$C$49 -> 4.825568 | T6: =MIN(D6-G6,S6) -> 4.825568 | U6: =MIN(I6-L6,MAX(0,S6-T6)) -> 0 | V6: =T6+U6 -> 4.825568
A7: 4 | B7: ='SOFR Curve'!B7 -> 46388 | C7: ='SOFR Curve'!C7 -> 0.0435 | D7: =H6 -> 45.611304 | E7: =MAX(C7,Assumptions!$C$13)+Assumptions!$C$12/10000 -> 0.0985 | F7: =D7*E7/4 -> 1.1231784 | G7: =MIN(D7,Assumptions!$C$11*Assumptions!$C$15/4) -> 0.15 | H7: =D7-G7-T7 -> 40.451813 | I7: =M6 -> 40 | J7: =MAX(C7,Assumptions!$C$20)+Assumptions!$C$19/10000 -> 0.1235 | K7: =I7*J7/4 -> 1.235 | L7: =MIN(I7,Assumptions!$C$18*Assumptions!$C$22/4) -> 0 | M7: =I7-L7-U7 -> 40 | N7: =D7+I7 -> 85.611304 | O7: =F7+K7 -> 2.3581784 | P7: =G7+L7 -> 0.15 | Q7: =H7+M7 -> 80.451813 | R7: =Assumptions!$C$7*(1+Assumptions!$C$8)^(A7/4)/4 -> 13.125 | S7: =MAX(0,R7*Assumptions!$C$48-O7-P7)*Assumptions!$C$49 -> 5.0094912 | T7: =MIN(D7-G7,S7) -> 5.0094912 | U7: =MIN(I7-L7,MAX(0,S7-T7)) -> 0 | V7: =T7+U7 -> 5.0094912
A8: 5 | B8: ='SOFR Curve'!B8 -> 46478 | C8: ='SOFR Curve'!C8 -> 0.043 | D8: =H7 -> 40.451813 | E8: =MAX(C8,Assumptions!$C$13)+Assumptions!$C$12/10000 -> 0.098 | F8: =D8*E8/4 -> 0.99106941 | G8: =MIN(D8,Assumptions!$C$11*Assumptions!$C$15/4) -> 0.15 | H8: =D8-G8-T8 -> 35.104926 | I8: =M7 -> 40 | J8: =MAX(C8,Assumptions!$C$20)+Assumptions!$C$19/10000 -> 0.123 | K8: =I8*J8/4 -> 1.23 | L8: =MIN(I8,Assumptions!$C$18*Assumptions!$C$22/4) -> 0 | M8: =I8-L8-U8 -> 40 | N8: =D8+I8 -> 80.451813 | O8: =F8+K8 -> 2.2210694 | P8: =G8+L8 -> 0.15 | Q8: =H8+M8 -> 75.104926 | R8: =Assumptions!$C$7*(1+Assumptions!$C$8)^(A8/4)/4 -> 13.286073 | S8: =MAX(0,R8*Assumptions!$C$48-O8-P8)*Assumptions!$C$49 -> 5.1968863 | T8: =MIN(D8-G8,S8) -> 5.1968863 | U8: =MIN(I8-L8,MAX(0,S8-T8)) -> 0 | V8: =T8+U8 -> 5.1968863
A9: 6 | B9: ='SOFR Curve'!B9 -> 46569 | C9: ='SOFR Curve'!C9 -> 0.0425 | D9: =H8 -> 35.104926 | E9: =MAX(C9,Assumptions!$C$13)+Assumptions!$C$12/10000 -> 0.0975 | F9: =D9*E9/4 -> 0.85568258 | G9: =MIN(D9,Assumptions!$C$11*Assumptions!$C$15/4) -> 0.15 | H9: =D9-G9-T9 -> 29.567149 | I9: =M8 -> 40 | J9: =MAX(C9,Assumptions!$C$20)+Assumptions!$C$19/10000 -> 0.1225 | K9: =I9*J9/4 -> 1.225 | L9: =MIN(I9,Assumptions!$C$18*Assumptions!$C$22/4) -> 0 | M9: =I9-L9-U9 -> 40 | N9: =D9+I9 -> 75.104926 | O9: =F9+K9 -> 2.0806826 | P9: =G9+L9 -> 0.15 | Q9: =H9+M9 -> 69.567149 | R9: =Assumptions!$C$7*(1+Assumptions!$C$8)^(A9/4)/4 -> 13.449123 | S9: =MAX(0,R9*Assumptions!$C$48-O9-P9)*Assumptions!$C$49 -> 5.3877776 | T9: =MIN(D9-G9,S9) -> 5.3877776 | U9: =MIN(I9-L9,MAX(0,S9-T9)) -> 0 | V9: =T9+U9 -> 5.3877776
A10: 7 | B10: ='SOFR Curve'!B10 -> 46661 | C10: ='SOFR Curve'!C10 -> 0.042 | D10: =H9 -> 29.567149 | E10: =MAX(C10,Assumptions!$C$13)+Assumptions!$C$12/10000 -> 0.097 | F10: =D10*E10/4 -> 0.71700335 | G10: =MIN(D10,Assumptions!$C$11*Assumptions!$C$15/4) -> 0.15 | H10: =D10-G10-T10 -> 23.83496 | I10: =M9 -> 40 | J10: =MAX(C10,Assumptions!$C$20)+Assumptions!$C$19/10000 -> 0.122 | K10: =I10*J10/4 -> 1.22 | L10: =MIN(I10,Assumptions!$C$18*Assumptions!$C$22/4) -> 0 | M10: =I10-L10-U10 -> 40 | N10: =D10+I10 -> 69.567149 | O10: =F10+K10 -> 1.9370034 | P10: =G10+L10 -> 0.15 | Q10: =H10+M10 -> 63.83496 | R10: =Assumptions!$C$7*(1+Assumptions!$C$8)^(A10/4)/4 -> 13.614174 | S10: =MAX(0,R10*Assumptions!$C$48-O10-P10)*Assumptions!$C$49 -> 5.5821887 | T10: =MIN(D10-G10,S10) -> 5.5821887 | U10: =MIN(I10-L10,MAX(0,S10-T10)) -> 0 | V10: =T10+U10 -> 5.5821887
A11: 8 | B11: ='SOFR Curve'!B11 -> 46753 | C11: ='SOFR Curve'!C11 -> 0.0415 | D11: =H10 -> 23.83496 | E11: =MAX(C11,Assumptions!$C$13)+Assumptions!$C$12/10000 -> 0.0965 | F11: =D11*E11/4 -> 0.57501841 | G11: =MIN(D11,Assumptions!$C$11*Assumptions!$C$15/4) -> 0.15 | H11: =D11-G11-T11 -> 17.904818 | I11: =M10 -> 40 | J11: =MAX(C11,Assumptions!$C$20)+Assumptions!$C$19/10000 -> 0.1215 | K11: =I11*J11/4 -> 1.215 | L11: =MIN(I11,Assumptions!$C$18*Assumptions!$C$22/4) -> 0 | M11: =I11-L11-U11 -> 40 | N11: =D11+I11 -> 63.83496 | O11: =F11+K11 -> 1.7900184 | P11: =G11+L11 -> 0.15 | Q11: =H11+M11 -> 57.904818 | R11: =Assumptions!$C$7*(1+Assumptions!$C$8)^(A11/4)/4 -> 13.78125 | S11: =MAX(0,R11*Assumptions!$C$48-O11-P11)*Assumptions!$C$49 -> 5.7801424 | T11: =MIN(D11-G11,S11) -> 5.7801424 | U11: =MIN(I11-L11,MAX(0,S11-T11)) -> 0 | V11: =T11+U11 -> 5.7801424
A12: 9 | B12: ='SOFR Curve'!B12 -> 46844 | C12: ='SOFR Curve'!C12 -> 0.041 | D12: =H11 -> 17.904818 | E12: =MAX(C12,Assumptions!$C$13)+Assumptions!$C$12/10000 -> 0.096 | F12: =D12*E12/4 -> 0.42971562 | G12: =MIN(D12,Assumptions!$C$11*Assumptions!$C$15/4) -> 0.15 | H12: =D12-G12-T12 -> 11.773156 | I12: =M11 -> 40 | J12: =MAX(C12,Assumptions!$C$20)+Assumptions!$C$19/10000 -> 0.121 | K12: =I12*J12/4 -> 1.21 | L12: =MIN(I12,Assumptions!$C$18*Assumptions!$C$22/4) -> 0 | M12: =I12-L12-U12 -> 40 | N12: =D12+I12 -> 57.904818 | O12: =F12+K12 -> 1.6397156 | P12: =G12+L12 -> 0.15 | Q12: =H12+M12 -> 51.773156 | R12: =Assumptions!$C$7*(1+Assumptions!$C$8)^(A12/4)/4 -> 13.950377 | S12: =MAX(0,R12*Assumptions!$C$48-O12-P12)*Assumptions!$C$49 -> 5.9816611 | T12: =MIN(D12-G12,S12) -> 5.9816611 | U12: =MIN(I12-L12,MAX(0,S12-T12)) -> 0 | V12: =T12+U12 -> 5.9816611
A13: 10 | B13: ='SOFR Curve'!B13 -> 46935 | C13: ='SOFR Curve'!C13 -> 0.0405 | D13: =H12 -> 11.773156 | E13: =MAX(C13,Assumptions!$C$13)+Assumptions!$C$12/10000 -> 0.0955 | F13: =D13*E13/4 -> 0.28108411 | G13: =MIN(D13,Assumptions!$C$11*Assumptions!$C$15/4) -> 0.15 | H13: =D13-G13-T13 -> 5.4363905 | I13: =M12 -> 40 | J13: =MAX(C13,Assumptions!$C$20)+Assumptions!$C$19/10000 -> 0.1205 | K13: =I13*J13/4 -> 1.205 | L13: =MIN(I13,Assumptions!$C$18*Assumptions!$C$22/4) -> 0 | M13: =I13-L13-U13 -> 40 | N13: =D13+I13 -> 51.773156 | O13: =F13+K13 -> 1.4860841 | P13: =G13+L13 -> 0.15 | Q13: =H13+M13 -> 45.436391 | R13: =Assumptions!$C$7*(1+Assumptions!$C$8)^(A13/4)/4 -> 14.121579 | S13: =MAX(0,R13*Assumptions!$C$48-O13-P13)*Assumptions!$C$49 -> 6.1867659 | T13: =MIN(D13-G13,S13) -> 6.1867659 | U13: =MIN(I13-L13,MAX(0,S13-T13)) -> 0 | V13: =T13+U13 -> 6.1867659
A14: 11 | B14: ='SOFR Curve'!B14 -> 47027 | C14: ='SOFR Curve'!C14 -> 0.04 | D14: =H13 -> 5.4363905 | E14: =MAX(C14,Assumptions!$C$13)+Assumptions!$C$12/10000 -> 0.095 | F14: =D14*E14/4 -> 0.12911428 | G14: =MIN(D14,Assumptions!$C$11*Assumptions!$C$15/4) -> 0.15 | H14: =D14-G14-T14 -> 0 | I14: =M13 -> 40 | J14: =MAX(C14,Assumptions!$C$20)+Assumptions!$C$19/10000 -> 0.12 | K14: =I14*J14/4 -> 1.2 | L14: =MIN(I14,Assumptions!$C$18*Assumptions!$C$22/4) -> 0 | M14: =I14-L14-U14 -> 38.890913 | N14: =D14+I14 -> 45.436391 | O14: =F14+K14 -> 1.3291143 | P14: =G14+L14 -> 0.15 | Q14: =H14+M14 -> 38.890913 | R14: =Assumptions!$C$7*(1+Assumptions!$C$8)^(A14/4)/4 -> 14.294882 | S14: =MAX(0,R14*Assumptions!$C$48-O14-P14)*Assumptions!$C$49 -> 6.3954775 | T14: =MIN(D14-G14,S14) -> 5.2863905 | U14: =MIN(I14-L14,MAX(0,S14-T14)) -> 1.109087 | V14: =T14+U14 -> 6.3954775
A15: 12 | B15: ='SOFR Curve'!B15 -> 47119 | C15: ='SOFR Curve'!C15 -> 0.0395 | D15: =H14 -> 0 | E15: =MAX(C15,Assumptions!$C$13)+Assumptions!$C$12/10000 -> 0.0945 | F15: =D15*E15/4 -> 0 | G15: =MIN(D15,Assumptions!$C$11*Assumptions!$C$15/4) -> 0 | H15: =D15-G15-T15 -> 0 | I15: =M14 -> 38.890913 | J15: =MAX(C15,Assumptions!$C$20)+Assumptions!$C$19/10000 -> 0.1195 | K15: =I15*J15/4 -> 1.161866 | L15: =MIN(I15,Assumptions!$C$18*Assumptions!$C$22/4) -> 0 | M15: =I15-L15-U15 -> 32.165398 | N15: =D15+I15 -> 38.890913 | O15: =F15+K15 -> 1.161866 | P15: =G15+L15 -> 0 | Q15: =H15+M15 -> 32.165398 | R15: =Assumptions!$C$7*(1+Assumptions!$C$8)^(A15/4)/4 -> 14.470313 | S15: =MAX(0,R15*Assumptions!$C$48-O15-P15)*Assumptions!$C$49 -> 6.7255145 | T15: =MIN(D15-G15,S15) -> 0 | U15: =MIN(I15-L15,MAX(0,S15-T15)) -> 6.7255145 | V15: =T15+U15 -> 6.7255145
A16: 13 | B16: ='SOFR Curve'!B16 -> 47209 | C16: ='SOFR Curve'!C16 -> 0.039 | D16: =H15 -> 0 | E16: =MAX(C16,Assumptions!$C$13)+Assumptions!$C$12/10000 -> 0.094 | F16: =D16*E16/4 -> 0 | G16: =MIN(D16,Assumptions!$C$11*Assumptions!$C$15/4) -> 0 | H16: =D16-G16-T16 -> 0 | I16: =M15 -> 32.165398 | J16: =MAX(C16,Assumptions!$C$20)+Assumptions!$C$19/10000 -> 0.119 | K16: =I16*J16/4 -> 0.9569206 | L16: =MIN(I16,Assumptions!$C$18*Assumptions!$C$22/4) -> 0 | M16: =I16-L16-U16 -> 25.192944 | N16: =D16+I16 -> 32.165398 | O16: =F16+K16 -> 0.9569206 | P16: =G16+L16 -> 0 | Q16: =H16+M16 -> 25.192944 | R16: =Assumptions!$C$7*(1+Assumptions!$C$8)^(A16/4)/4 -> 14.647896 | S16: =MAX(0,R16*Assumptions!$C$48-O16-P16)*Assumptions!$C$49 -> 6.9724547 | T16: =MIN(D16-G16,S16) -> 0 | U16: =MIN(I16-L16,MAX(0,S16-T16)) -> 6.9724547 | V16: =T16+U16 -> 6.9724547
... A23: 20 | B23: ='SOFR Curve'!B23 -> 47849 | C23: ='SOFR Curve'!C23 -> 0.0355 | D23: =H22 -> 0 | E23: =MAX(C23,Assumptions!$C$13)+Assumptions!$C$12/10000 -> 0.0905 | F23: =D23*E23/4 -> 0 | G23: =MIN(D23,Assumptions!$C$11*Assumptions!$C$15/4) -> 0 | H23: =D23-G23-T23 -> 0 | I23: =M22 -> 0 | J23: =MAX(C23,Assumptions!$C$20)+Assumptions!$C$19/10000 -> 0.1155 | K23: =I23*J23/4 -> 0 | L23: =MIN(I23,Assumptions!$C$18*Assumptions!$C$22/4) -> 0 | M23: =I23-L23-U23 -> 0 | N23: =D23+I23 -> 0 | O23: =F23+K23 -> 0 | P23: =G23+L23 -> 0 | Q23: =H23+M23 -> 0 | R23: =Assumptions!$C$7*(1+Assumptions!$C$8)^(A23/4)/4 -> 15.95352 | S23: =MAX(0,R23*Assumptions!$C$48-O23-P23)*Assumptions!$C$49 -> 8.3755978 | T23: =MIN(D23-G23,S23) -> 0 | U23: =MIN(I23-L23,MAX(0,S23-T23)) -> 0 | V23: =T23+U23 -> 0

Sheet Covenants
B1: COVENANT TESTING
A3: Period | B3: Date | C3: LTM EBITDA | D3: Total Debt | E3: Leverage (x) | F3: Max Leverage (x) | G3: Cushion (x) | H3: Cash Int (Qtr) | I3: LTM Cash Int | J3: Interest Coverage (x) | K3: Min ICR (x) | L3: Status
A4: ='Debt Schedule'!A4 -> 1 | B4: ='Debt Schedule'!B4 -> 46113 | C4: =Assumptions!$C$7*(1+Assumptions!$C$8)^(A4/4) -> 50.613612 | D4: ='Debt Schedule'!Q4 -> 95.381963 | E4: =D4/C4 -> 1.8845121 | F4: =IF(A4<=8,Assumptions!$C$29,Assumptions!$C$30) -> 6.5 | G4: =F4-E4 -> 4.6154879 | H4: ='Debt Schedule'!O4 -> 2.75 | I4: =SUM(OFFSET(H4,-MIN(3,A4-1),0,MIN(4,A4),1))*4/MIN(4,A4) -> 11 | J4: =C4/I4 -> 4.6012374 | K4: =Assumptions!$C$31 -> 2 | L4: =IF(AND(E4<=F4,J4>=K4),"Pass","Fail") -> Pass
A5: ='Debt Schedule'!A5 -> 2 | B5: ='Debt Schedule'!B5 -> 46204 | C5: =Assumptions!$C$7*(1+Assumptions!$C$8)^(A5/4) -> 51.234754 | D5: ='Debt Schedule'!Q5 -> 90.586872 | E5: =D5/C5 -> 1.7680747 | F5: =IF(A5<=8,Assumptions!$C$29,Assumptions!$C$30) -> 6.5 | G5: =F5-E5 -> 4.7319253 | H5: ='Debt Schedule'!O5 -> 2.6226263 | I5: =SUM(OFFSET(H5,-MIN(3,A5-1),0,MIN(4,A5),1))*4/MIN(4,A5) -> 10.745253 | J5: =C5/I5 -> 4.7681293 | K5: =Assumptions!$C$31 -> 2 | L5: =IF(AND(E5<=F5,J5>=K5),"Pass","Fail") -> Pass
A6: ='Debt Schedule'!A6 -> 3 | B6: ='Debt Schedule'!B6 -> 46296 | C6: =Assumptions!$C$7*(1+Assumptions!$C$8)^(A6/4) -> 51.863519 | D6: ='Debt Schedule'!Q6 -> 85.611304 | E6: =D6/C6 -> 1.6507037 | F6: =IF(A6<=8,Assumptions!$C$29,Assumptions!$C$30) -> 6.5 | G6: =F6-E6 -> 4.8492963 | H6: ='Debt Schedule'!O6 -> 2.4920251 | I6: =SUM(OFFSET(H6,-MIN(3,A6-1),0,MIN(4,A6),1))*4/MIN(4,A6) -> 10.486202 | J6: =C6/I6 -> 4.9458821 | K6: =Assumptions!$C$31 -> 2 | L6: =IF(AND(E6<=F6,J6>=K6),"Pass","Fail") -> Pass
A7: ='Debt Schedule'!A7 -> 4 | B7: ='Debt Schedule'!B7 -> 46388 | C7: =Assumptions!$C$7*(1+Assumptions!$C$8)^(A7/4) -> 52.5 | D7: ='Debt Schedule'!Q7 -> 80.451813 | E7: =D7/C7 -> 1.5324155 | F7: =IF(A7<=8,Assumptions!$C$29,Assumptions!$C$30) -> 6.5 | G7: =F7-E7 -> 4.9675845 | H7: ='Debt Schedule'!O7 -> 2.3581784 | I7: =SUM(OFFSET(H7,-MIN(3,A7-1),0,MIN(4,A7),1))*4/MIN(4,A7) -> 10.22283 | J7: =C7/I7 -> 5.1355643 | K7: =Assumptions!$C$31 -> 2 | L7: =IF(AND(E7<=F7,J7>=K7),"Pass","Fail") -> Pass
A8: ='Debt Schedule'!A8 -> 5 | B8: ='Debt Schedule'!B8 -> 46478 | C8: =Assumptions!$C$7*(1+Assumptions!$C$8)^(A8/4) -> 53.144292 | D8: ='Debt Schedule'!Q8 -> 75.104926 | E8: =D8/C8 -> 1.4132266 | F8: =IF(A8<=8,Assumptions!$C$29,Assumptions!$C$30) -> 6.5 | G8: =F8-E8 -> 5.0867734 | H8: ='Debt Schedule'!O8 -> 2.2210694 | I8: =SUM(OFFSET(H8,-MIN(3,A8-1),0,MIN(4,A8),1))*4/MIN(4,A8) -> 9.6938992 | J8: =C8/I8 -> 5.4822411 | K8: =Assumptions!$C$31 -> 2 | L8: =IF(AND(E8<=F8,J8>=K8),"Pass","Fail") -> Pass
A9: ='Debt Schedule'!A9 -> 6 | B9: ='Debt Schedule'!B9 -> 46569 | C9: =Assumptions!$C$7*(1+Assumptions!$C$8)^(A9/4) -> 53.796492 | D9: ='Debt Schedule'!Q9 -> 69.567149 | E9: =D9/C9 -> 1.293154 | F9: =IF(A9<=8,Assumptions!$C$29,Assumptions!$C$30) -> 6.5 | G9: =F9-E9 -> 5.206846 | H9: ='Debt Schedule'!O9 -> 2.0806826 | I9: =SUM(OFFSET(H9,-MIN(3,A9-1),0,MIN(4,A9),1))*4/MIN(4,A9) -> 9.1519554 | J9: =C9/I9 -> 5.8781418 | K9: =Assumptions!$C$31 -> 2 | L9: =IF(AND(E9<=F9,J9>=K9),"Pass","Fail") -> Pass
A10: ='Debt Schedule'!A10 -> 7 | B10: ='Debt Schedule'!B10 -> 46661 | C10: =Assumptions!$C$7*(1+Assumptions!$C$8)^(A10/4) -> 54.456695 | D10: ='Debt Schedule'!Q10 -> 63.83496 | E10: =D10/C10 -> 1.1722151 | F10: =IF(A10<=8,Assumptions!$C$29,Assumptions!$C$30) -> 6.5 | G10: =F10-E10 -> 5.3277849 | H10: ='Debt Schedule'!O10 -> 1.9370034 | I10: =SUM(OFFSET(H10,-MIN(3,A10-1),0,MIN(4,A10),1))*4/MIN(4,A10) -> 8.5969337 | J10: =C10/I10 -> 6.3344323 | K10: =Assumptions!$C$31 -> 2 | L10: =IF(AND(E10<=F10,J10>=K10),"Pass","Fail") -> Pass
A11: ='Debt Schedule'!A11 -> 8 | B11: ='Debt Schedule'!B11 -> 46753 | C11: =Assumptions!$C$7*(1+Assumptions!$C$8)^(A11/4) -> 55.125 | D11: ='Debt Schedule'!Q11 -> 57.904818 | E11: =D11/C11 -> 1.0504275 | F11: =IF(A11<=8,Assumptions!$C$29,Assumptions!$C$30) -> 6.5 | G11: =F11-E11 -> 5.4495725 | H11: ='Debt Schedule'!O11 -> 1.7900184 | I11: =SUM(OFFSET(H11,-MIN(3,A11-1),0,MIN(4,A11),1))*4/MIN(4,A11) -> 8.0287737 | J11: =C11/I11 -> 6.8659302 | K11: =Assumptions!$C$31 -> 2 | L11: =IF(AND(E11<=F11,J11>=K11),"Pass","Fail") -> Pass
A12: ='Debt Schedule'!A12 -> 9 | B12: ='Debt Schedule'!B12 -> 46844 | C12: =Assumptions!$C$7*(1+Assumptions!$C$8)^(A12/4) -> 55.801507 | D12: ='Debt Schedule'!Q12 -> 51.773156 | E12: =D12/C12 -> 0.92780929 | F12: =IF(A12<=8,Assumptions!$C$29,Assumptions!$C$30) -> 6 | G12: =F12-E12 -> 5.0721907 | H12: ='Debt Schedule'!O12 -> 1.6397156 | I12: =SUM(OFFSET(H12,-MIN(3,A12-1),0,MIN(4,A12),1))*4/MIN(4,A12) -> 7.44742 | J12: =C12/I12 -> 7.49273 | K12: =Assumptions!$C$31 -> 2 | L12: =IF(AND(E12<=F12,J12>=K12),"Pass","Fail") -> Pass
A13: ='Debt Schedule'!A13 -> 10 | B13: ='Debt Schedule'!B13 -> 46935 | C13: =Assumptions!$C$7*(1+Assumptions!$C$8)^(A13/4) -> 56.486316 | D13: ='Debt Schedule'!Q13 -> 45.436391 | E13: =D13/C13 -> 0.80437872 | F13: =IF(A13<=8,Assumptions!$C$29,Assumptions!$C$30) -> 6 | G13: =F13-E13 -> 5.1956213 | H13: ='Debt Schedule'!O13 -> 1.4860841 | I13: =SUM(OFFSET(H13,-MIN(3,A13-1),0,MIN(4,A13),1))*4/MIN(4,A13) -> 6.8528215 | J13: =C13/I13 -> 8.2427824 | K13: =Assumptions!$C$31 -> 2 | L13: =IF(AND(E13<=F13,J13>=K13),"Pass","Fail") -> Pass
A14: ='Debt Schedule'!A14 -> 11 | B14: ='Debt Schedule'!B14 -> 47027 | C14: =Assumptions!$C$7*(1+Assumptions!$C$8)^(A14/4) -> 57.179529 | D14: ='Debt Schedule'!Q14 -> 38.890913 | E14: =D14/C14 -> 0.68015448 | F14: =IF(A14<=8,Assumptions!$C$29,Assumptions!$C$30) -> 6 | G14: =F14-E14 -> 5.3198455 | H14: ='Debt Schedule'!O14 -> 1.3291143 | I14: =SUM(OFFSET(H14,-MIN(3,A14-1),0,MIN(4,A14),1))*4/MIN(4,A14) -> 6.2449324 | J14: =C14/I14 -> 9.1561486 | K14: =Assumptions!$C$31 -> 2 | L14: =IF(AND(E14<=F14,J14>=K14),"Pass","Fail") -> Pass
A15: ='Debt Schedule'!A15 -> 12 | B15: ='Debt Schedule'!B15 -> 47119 | C15: =Assumptions!$C$7*(1+Assumptions!$C$8)^(A15/4) -> 57.88125 | D15: ='Debt Schedule'!Q15 -> 32.165398 | E15: =D15/C15 -> 0.55571361 | F15: =IF(A15<=8,Assumptions!$C$29,Assumptions!$C$30) -> 6 | G15: =F15-E15 -> 5.4442864 | H15: ='Debt Schedule'!O15 -> 1.161866 | I15: =SUM(OFFSET(H15,-MIN(3,A15-1),0,MIN(4,A15),1))*4/MIN(4,A15) -> 5.61678 | J15: =C15/I15 -> 10.305059 | K15: =Assumptions!$C$31 -> 2 | L15: =IF(AND(E15<=F15,J15>=K15),"Pass","Fail") -> Pass
... A23: ='Debt Schedule'!A23 -> 20 | B23: ='Debt Schedule'!B23 -> 47849 | C23: =Assumptions!$C$7*(1+Assumptions!$C$8)^(A23/4) -> 63.814078 | D23: ='Debt Schedule'!Q23 -> 0 | E23: =D23/C23 -> 0 | F23: =IF(A23<=8,Assumptions!$C$29,Assumptions!$C$30) -> 6 | G23: =F23-E23 -> 6 | H23: ='Debt Schedule'!O23 -> 0 | I23: =SUM(OFFSET(H23,-MIN(3,A23-1),0,MIN(4,A23),1))*4/MIN(4,A23) -> 0.080142771 | J23: =C23/I23 -> 796.25495 | K23: =Assumptions!$C$31 -> 2 | L23: =IF(AND(E23<=F23,J23>=K23),"Pass","Fail") -> Pass

Sheet Returns
B1: LENDER CASH FLOWS & RETURNS
A3: Period | B3: Date | C3: CF - Tranche A | D3: CF - Tranche B | E3: CF - Total
A4: 0 | B4: =Assumptions!$C$5 -> 2026-01-01 | C4: =-Assumptions!$C$11*Assumptions!$C$14 -> -59.4 | D4: =-Assumptions!$C$18*Assumptions!$C$21 -> -39.2 | E4: =C4+D4 -> -98.6
A5: 1 | B5: ='Debt Schedule'!B4 -> 46113 | C5: =IF(A5<Assumptions!$C$35,'Debt Schedule'!F4+'Debt Schedule'!G4+'Debt Schedule'!T4,IF(A5=Assumptions!$C$35,'Debt Schedule'!F4+'Debt Schedule'!G4+'Debt Schedule'!T4+'Debt Schedule'!H4*Assumptions!$C$45,0)) -> 6.1180365 | D5: =IF(A5<Assumptions!$C$35,'Debt Schedule'!K4+'Debt Schedule'!L4+'Debt Schedule'!U4,IF(A5=Assumptions!$C$35,'Debt Schedule'!K4+'Debt Schedule'!L4+'Debt Schedule'!U4+'Debt Schedule'!M4*Assumptions!$C$45,0)) -> 1.25 | E5: =C5+D5 -> 7.3680365
A6: 2 | B6: ='Debt Schedule'!B5 -> 46204 | C6: =IF(A6<Assumptions!$C$35,'Debt Schedule'!F5+'Debt Schedule'!G5+'Debt Schedule'!T5,IF(A6=Assumptions!$C$35,'Debt Schedule'!F5+'Debt Schedule'!G5+'Debt Schedule'!T5+'Debt Schedule'!H5*Assumptions!$C$45,0)) -> 6.172718 | D6: =IF(A6<Assumptions!$C$35,'Debt Schedule'!K5+'Debt Schedule'!L5+'Debt Schedule'!U5,IF(A6=Assumptions!$C$35,'Debt Schedule'!K5+'Debt Schedule'!L5+'Debt Schedule'!U5+'Debt Schedule'!M5*Assumptions!$C$45,0)) -> 1.245 | E6: =C6+D6 -> 7.417718
A7: 3 | B7: ='Debt Schedule'!B6 -> 46296 | C7: =IF(A7<Assumptions!$C$35,'Debt Schedule'!F6+'Debt Schedule'!G6+'Debt Schedule'!T6,IF(A7=Assumptions!$C$35,'Debt Schedule'!F6+'Debt Schedule'!G6+'Debt Schedule'!T6+'Debt Schedule'!H6*Assumptions!$C$45,0)) -> 6.2275931 | D7: =IF(A7<Assumptions!$C$35,'Debt Schedule'!K6+'Debt Schedule'!L6+'Debt Schedule'!U6,IF(A7=Assumptions!$C$35,'Debt Schedule'!K6+'Debt Schedule'!L6+'Debt Schedule'!U6+'Debt Schedule'!M6*Assumptions!$C$45,0)) -> 1.24 | E7: =C7+D7 -> 7.4675931
A8: 4 | B8: ='Debt Schedule'!B7 -> 46388 | C8: =IF(A8<Assumptions!$C$35,'Debt Schedule'!F7+'Debt Schedule'!G7+'Debt Schedule'!T7,IF(A8=Assumptions!$C$35,'Debt Schedule'!F7+'Debt Schedule'!G7+'Debt Schedule'!T7+'Debt Schedule'!H7*Assumptions!$C$45,0)) -> 6.2826696 | D8: =IF(A8<Assumptions!$C$35,'Debt Schedule'!K7+'Debt Schedule'!L7+'Debt Schedule'!U7,IF(A8=Assumptions!$C$35,'Debt Schedule'!K7+'Debt Schedule'!L7+'Debt Schedule'!U7+'Debt Schedule'!M7*Assumptions!$C$45,0)) -> 1.235 | E8: =C8+D8 -> 7.5176696
A9: 5 | B9: ='Debt Schedule'!B8 -> 46478 | C9: =IF(A9<Assumptions!$C$35,'Debt Schedule'!F8+'Debt Schedule'!G8+'Debt Schedule'!T8,IF(A9=Assumptions!$C$35,'Debt Schedule'!F8+'Debt Schedule'!G8+'Debt Schedule'!T8+'Debt Schedule'!H8*Assumptions!$C$45,0)) -> 6.3379557 | D9: =IF(A9<Assumptions!$C$35,'Debt Schedule'!K8+'Debt Schedule'!L8+'Debt Schedule'!U8,IF(A9=Assumptions!$C$35,'Debt Schedule'!K8+'Debt Schedule'!L8+'Debt Schedule'!U8+'Debt Schedule'!M8*Assumptions!$C$45,0)) -> 1.23 | E9: =C9+D9 -> 7.5679557
A10: 6 | B10: ='Debt Schedule'!B9 -> 46569 | C10: =IF(A10<Assumptions!$C$35,'Debt Schedule'!F9+'Debt Schedule'!G9+'Debt Schedule'!T9,IF(A10=Assumptions!$C$35,'Debt Schedule'!F9+'Debt Schedule'!G9+'Debt Schedule'!T9+'Debt Schedule'!H9*Assumptions!$C$45,0)) -> 6.3934602 | D10: =IF(A10<Assumptions!$C$35,'Debt Schedule'!K9+'Debt Schedule'!L9+'Debt Schedule'!U9,IF(A10=Assumptions!$C$35,'Debt Schedule'!K9+'Debt Schedule'!L9+'Debt Schedule'!U9+'Debt Schedule'!M9*Assumptions!$C$45,0)) -> 1.225 | E10: =C10+D10 -> 7.6184602
A11: 7 | B11: ='Debt Schedule'!B10 -> 46661 | C11: =IF(A11<Assumptions!$C$35,'Debt Schedule'!F10+'Debt Schedule'!G10+'Debt Schedule'!T10,IF(A11=Assumptions!$C$35,'Debt Schedule'!F10+'Debt Schedule'!G10+'Debt Schedule'!T10+'Debt Schedule'!H10*Assumptions!$C$45,0)) -> 6.449192 | D11: =IF(A11<Assumptions!$C$35,'Debt Schedule'!K10+'Debt Schedule'!L10+'Debt Schedule'!U10,IF(A11=Assumptions!$C$35,'Debt Schedule'!K10+'Debt Schedule'!L10+'Debt Schedule'!U10+'Debt Schedule'!M10*Assumptions!$C$45,0)) -> 1.22 | E11: =C11+D11 -> 7.669192
A12: 8 | B12: ='Debt Schedule'!B11 -> 46753 | C12: =IF(A12<Assumptions!$C$35,'Debt Schedule'!F11+'Debt Schedule'!G11+'Debt Schedule'!T11,IF(A12=Assumptions!$C$35,'Debt Schedule'!F11+'Debt Schedule'!G11+'Debt Schedule'!T11+'Debt Schedule'!H11*Assumptions!$C$45,0)) -> 6.5051609 | D12: =IF(A12<Assumptions!$C$35,'Debt Schedule'!K11+'Debt Schedule'!L11+'Debt Schedule'!U11,IF(A12=Assumptions!$C$35,'Debt Schedule'!K11+'Debt Schedule'!L11+'Debt Schedule'!U11+'Debt Schedule'!M11*Assumptions!$C$45,0)) -> 1.215 | E12: =C12+D12 -> 7.7201609
A13: 9 | B13: ='Debt Schedule'!B12 -> 46844 | C13: =IF(A13<Assumptions!$C$35,'Debt Schedule'!F12+'Debt Schedule'!G12+'Debt Schedule'!T12,IF(A13=Assumptions!$C$35,'Debt Schedule'!F12+'Debt Schedule'!G12+'Debt Schedule'!T12+'Debt Schedule'!H12*Assumptions!$C$45,0)) -> 6.5613767 | D13: =IF(A13<Assumptions!$C$35,'Debt Schedule'!K12+'Debt Schedule'!L12+'Debt Schedule'!U12,IF(A13=Assumptions!$C$35,'Debt Schedule'!K12+'Debt Schedule'!L12+'Debt Schedule'!U12+'Debt Schedule'!M12*Assumptions!$C$45,0)) -> 1.21 | E13: =C13+D13 -> 7.7713767
A14: 10 | B14: ='Debt Schedule'!B13 -> 46935 | C14: =IF(A14<Assumptions!$C$35,'Debt Schedule'!F13+'Debt Schedule'!G13+'Debt Schedule'!T13,IF(A14=Assumptions!$C$35,'Debt Schedule'!F13+'Debt Schedule'!G13+'Debt Schedule'!T13+'Debt Schedule'!H13*Assumptions!$C$45,0)) -> 6.61785 | D14: =IF(A14<Assumptions!$C$35,'Debt Schedule'!K13+'Debt Schedule'!L13+'Debt Schedule'!U13,IF(A14=Assumptions!$C$35,'Debt Schedule'!K13+'Debt Schedule'!L13+'Debt Schedule'!U13+'Debt Schedule'!M13*Assumptions!$C$45,0)) -> 1.205 | E14: =C14+D14 -> 7.82285
A15: 11 | B15: ='Debt Schedule'!B14 -> 47027 | C15: =IF(A15<Assumptions!$C$35,'Debt Schedule'!F14+'Debt Schedule'!G14+'Debt Schedule'!T14,IF(A15=Assumptions!$C$35,'Debt Schedule'!F14+'Debt Schedule'!G14+'Debt Schedule'!T14+'Debt Schedule'!H14*Assumptions!$C$45,0)) -> 5.5655048 | D15: =IF(A15<Assumptions!$C$35,'Debt Schedule'!K14+'Debt Schedule'!L14+'Debt Schedule'!U14,IF(A15=Assumptions!$C$35,'Debt Schedule'!K14+'Debt Schedule'!L14+'Debt Schedule'!U14+'Debt Schedule'!M14*Assumptions!$C$45,0)) -> 2.309087 | E15: =C15+D15 -> 7.8745918
A16: 12 | B16: ='Debt Schedule'!B15 -> 47119 | C16: =IF(A16<Assumptions!$C$35,'Debt Schedule'!F15+'Debt Schedule'!G15+'Debt Schedule'!T15,IF(A16=Assumptions!$C$35,'Debt Schedule'!F15+'Debt Schedule'!G15+'Debt Schedule'!T15+'Debt Schedule'!H15*Assumptions!$C$45,0)) -> 0 | D16: =IF(A16<Assumptions!$C$35,'Debt Schedule'!K15+'Debt Schedule'!L15+'Debt Schedule'!U15,IF(A16=Assumptions!$C$35,'Debt Schedule'!K15+'Debt Schedule'!L15+'Debt Schedule'!U15+'Debt Schedule'!M15*Assumptions!$C$45,0)) -> 40.052779 | E16: =C16+D16 -> 40.052779
... A24: 20 | B24: ='Debt Schedule'!B23 -> 47849 | C24: =IF(A24<Assumptions!$C$35,'Debt Schedule'!F23+'Debt Schedule'!G23+'Debt Schedule'!T23,IF(A24=Assumptions!$C$35,'Debt Schedule'!F23+'Debt Schedule'!G23+'Debt Schedule'!T23+'Debt Schedule'!H23*Assumptions!$C$45,0)) -> 0 | D24: =IF(A24<Assumptions!$C$35,'Debt Schedule'!K23+'Debt Schedule'!L23+'Debt Schedule'!U23,IF(A24=Assumptions!$C$35,'Debt Schedule'!K23+'Debt Schedule'!L23+'Debt Schedule'!U23+'Debt Schedule'!M23*Assumptions!$C$45,0)) -> 0 | E24: =C24+D24 -> 0
B26: SUMMARY RETURNS
A27: Tranche A IRR (ann.) | B27: =XIRR(C4:C24,B4:B24) -> 0.10994733
A28: Tranche B IRR (ann.) | B28: =XIRR(D4:D24,B4:B24) -> 0.13708904
A29: Blended IRR (ann.) | B29: =XIRR(E4:E24,B4:B24) -> 0.12467577
A30: Tranche A MOIC | B30: =SUMIF(C5:C24,">0")/ABS(C4) -> 1.1655138
A31: Tranche B MOIC | B31: =SUMIF(D5:D24,">0")/ABS(D4) -> 1.3937976
A32: Blended MOIC | B32: =SUMIF(E5:E24,">0")/ABS(E4) -> 1.2562716
