Workbook

Sheet Assumptions
B1: Assumptions
B3: Global Assumptions
B4: Tax rate | C4: 0.25
B5: Interest rate on debt | C5: 0.05
B6: WACC / Discount rate | C6: 0.1
B7: Terminal growth rate | C7: 0.025
B8: Accounts receivable days (DSO) | C8: 45
B9: Inventory days | C9: 30
B10: Accounts payable days (DPO) | C10: 40
B11: Shares outstanding | C11: 40000000
B13: Operating Assumptions
C14: 2025A | D14: 2026E | E14: 2027E | F14: 2028E | G14: 2029E | H14: 2030E
B15: Revenue growth % | D15: 0.1 | E15: 0.09 | F15: 0.08 | G15: 0.07 | H15: 0.06
B16: COGS % of revenue | C16: 0.6 | D16: 0.6 | E16: 0.6 | F16: 0.6 | G16: 0.6 | H16: 0.6
B17: SG&A % of revenue | C17: 0.15 | D17: 0.15 | E17: 0.15 | F17: 0.15 | G17: 0.15 | H17: 0.15
B18: D&A % of revenue | C18: 0.03 | D18: 0.03 | E18: 0.03 | F18: 0.03 | G18: 0.03 | H18: 0.03
B19: CapEx % of revenue | C19: 0.04 | D19: 0.04 | E19: 0.04 | F19: 0.04 | G19: 0.04 | H19: 0.04

Sheet IS
B1: Income Statement
C2: 2025A | D2: 2026E | E2: 2027E | F2: 2028E | G2: 2029E | H2: 2030E
B4: Revenue | C4: 500000000 | D4: =C4*(1+Assumptions!D15) | E4: =D4*(1+Assumptions!E15) | F4: =E4*(1+Assumptions!F15) | G4: =F4*(1+Assumptions!G15) | H4: =G4*(1+Assumptions!H15)
B5: Revenue growth % | D5: =D4/C4-1 | E5: =E4/D4-1 | F5: =F4/E4-1 | G5: =G4/F4-1 | H5: =H4/G4-1
B6: COGS | C6: =C4*Assumptions!C16 | D6: =D4*Assumptions!D16 | E6: =E4*Assumptions!E16 | F6: =F4*Assumptions!F16 | G6: =G4*Assumptions!G16 | H6: =H4*Assumptions!H16
B7: Gross Profit | C7: =C4-C6 | D7: =D4-D6 | E7: =E4-E6 | F7: =F4-F6 | G7: =G4-G6 | H7: =H4-H6
B8: Gross margin % | C8: =C7/C4 | D8: =D7/D4 | E8: =E7/E4 | F8: =F7/F4 | G8: =G7/G4 | H8: =H7/H4
B9: SG&A | C9: =C4*Assumptions!C17 | D9: =D4*Assumptions!D17 | E9: =E4*Assumptions!E17 | F9: =F4*Assumptions!F17 | G9: =G4*Assumptions!G17 | H9: =H4*Assumptions!H17
B10: EBITDA | C10: =C7-C9 | D10: =D7-D9 | E10: =E7-E9 | F10: =F7-F9 | G10: =G7-G9 | H10: =H7-H9
B11: EBITDA margin % | C11: =C10/C4 | D11: =D10/D4 | E11: =E10/E4 | F11: =F10/F4 | G11: =G10/G4 | H11: =H10/H4
B12: D&A | C12: =C4*Assumptions!C18 | D12: =D4*Assumptions!D18 | E12: =E4*Assumptions!E18 | F12: =F4*Assumptions!F18 | G12: =G4*Assumptions!G18 | H12: =H4*Assumptions!H18
B13: EBIT | C13: =C10-C12 | D13: =D10-D12 | E13: =E10-E12 | F13: =F10-F12 | G13: =G10-G12 | H13: =H10-H12
B14: Interest expense | C14: =BS!C14*Assumptions!$C$5 | D14: =BS!D14*Assumptions!$C$5 | E14: =BS!E14*Assumptions!$C$5 | F14: =BS!F14*Assumptions!$C$5 | G14: =BS!G14*Assumptions!$C$5 | H14: =BS!H14*Assumptions!$C$5
B15: EBT | C15: =C13-C14 | D15: =D13-D14 | E15: =E13-E14 | F15: =F13-F14 | G15: =G13-G14 | H15: =H13-H14
B16: Taxes | C16: =C15*Assumptions!$C$4 | D16: =D15*Assumptions!$C$4 | E16: =E15*Assumptions!$C$4 | F16: =F15*Assumptions!$C$4 | G16: =G15*Assumptions!$C$4 | H16: =H15*Assumptions!$C$4
B17: Net Income | C17: =C15-C16 | D17: =D15-D16 | E17: =E15-E16 | F17: =F15-F16 | G17: =G15-G16 | H17: =H15-H16

Sheet BS
B1: Balance Sheet
C2: 2025A | D2: 2026E | E2: 2027E | F2: 2028E | G2: 2029E | H2: 2030E
B3: Assets
B4: Cash | C4: 50000000 | D4: =C4+CFS!D19 | E4: =D4+CFS!E19 | F4: =E4+CFS!F19 | G4: =F4+CFS!G19 | H4: =G4+CFS!H19
B5: Accounts Receivable | C5: =IS!C4*Assumptions!$C$8/365 | D5: =IS!D4*Assumptions!$C$8/365 | E5: =IS!E4*Assumptions!$C$8/365 | F5: =IS!F4*Assumptions!$C$8/365 | G5: =IS!G4*Assumptions!$C$8/365 | H5: =IS!H4*Assumptions!$C$8/365
B6: Inventory | C6: =IS!C6*Assumptions!$C$9/365 | D6: =IS!D6*Assumptions!$C$9/365 | E6: =IS!E6*Assumptions!$C$9/365 | F6: =IS!F6*Assumptions!$C$9/365 | G6: =IS!G6*Assumptions!$C$9/365 | H6: =IS!H6*Assumptions!$C$9/365
B7: Total Current Assets | C7: =SUM(C4:C6) | D7: =SUM(D4:D6) | E7: =SUM(E4:E6) | F7: =SUM(F4:F6) | G7: =SUM(G4:G6) | H7: =SUM(H4:H6)
B8: PP&E, net | C8: 200000000 | D8: =C8+IS!D4*Assumptions!$C$19-IS!D12 | E8: =D8+IS!E4*Assumptions!$C$19-IS!E12 | F8: =E8+IS!F4*Assumptions!$C$19-IS!F12 | G8: =F8+IS!G4*Assumptions!$C$19-IS!G12 | H8: =G8+IS!H4*Assumptions!$C$19-IS!H12
B9: Total Assets | C9: =C7+C8 | D9: =D7+D8 | E9: =E7+E8 | F9: =F7+F8 | G9: =G7+G8 | H9: =H7+H8
B11: Liabilities
B12: Accounts Payable | C12: =IS!C6*Assumptions!$C$10/365 | D12: =IS!D6*Assumptions!$C$10/365 | E12: =IS!E6*Assumptions!$C$10/365 | F12: =IS!F6*Assumptions!$C$10/365 | G12: =IS!G6*Assumptions!$C$10/365 | H12: =IS!H6*Assumptions!$C$10/365
B13: Total Current Liabilities | C13: =C12 | D13: =D12 | E13: =E12 | F13: =F12 | G13: =G12 | H13: =H12
B14: Debt | C14: 100000000 | D14: =C14 | E14: =D14 | F14: =E14 | G14: =F14 | H14: =G14
B15: Total Liabilities | C15: =C13+C14 | D15: =D13+D14 | E15: =E13+E14 | F15: =F13+F14 | G15: =G13+G14 | H15: =H13+H14
B17: Equity
B18: Common Stock | C18: 150000000 | D18: =C18 | E18: =D18 | F18: =E18 | G18: =F18 | H18: =G18
B19: Retained Earnings | C19: =C9-C15-C18 | D19: =C19+IS!D17 | E19: =D19+IS!E17 | F19: =E19+IS!F17 | G19: =F19+IS!G17 | H19: =G19+IS!H17
B20: Total Equity | C20: =C18+C19 | D20: =D18+D19 | E20: =E18+E19 | F20: =F18+F19 | G20: =G18+G19 | H20: =H18+H19
B21: Total Liabilities & Equity | C21: =C15+C20 | D21: =D15+D20 | E21: =E15+E20 | F21: =F15+F20 | G21: =G15+G20 | H21: =H15+H20
B23: Check (Assets − Liab. & Equity) | C23: =C9-C21 | D23: =D9-D21 | E23: =E9-E21 | F23: =F9-F21 | G23: =G9-G21 | H23: =H9-H21

Sheet CFS
B1: Cash Flow Statement
D2: 2026E | E2: 2027E | F2: 2028E | G2: 2029E | H2: 2030E
B3: Operating Activities
B4: Net Income | D4: =IS!D17 | E4: =IS!E17 | F4: =IS!F17 | G4: =IS!G17 | H4: =IS!H17
B5: (+) D&A | D5: =IS!D12 | E5: =IS!E12 | F5: =IS!F12 | G5: =IS!G12 | H5: =IS!H12
B6: (-) Increase in Accounts Receivable | D6: =-(BS!D5-BS!C5) | E6: =-(BS!E5-BS!D5) | F6: =-(BS!F5-BS!E5) | G6: =-(BS!G5-BS!F5) | H6: =-(BS!H5-BS!G5)
B7: (-) Increase in Inventory | D7: =-(BS!D6-BS!C6) | E7: =-(BS!E6-BS!D6) | F7: =-(BS!F6-BS!E6) | G7: =-(BS!G6-BS!F6) | H7: =-(BS!H6-BS!G6)
B8: (+) Increase in Accounts Payable | D8: =BS!D12-BS!C12 | E8: =BS!E12-BS!D12 | F8: =BS!F12-BS!E12 | G8: =BS!G12-BS!F12 | H8: =BS!H12-BS!G12
B9: Cash from Operations | D9: =SUM(D4:D8) | E9: =SUM(E4:E8) | F9: =SUM(F4:F8) | G9: =SUM(G4:G8) | H9: =SUM(H4:H8)
B11: Investing Activities
B12: CapEx | D12: =-(IS!D4*Assumptions!$C$19) | E12: =-(IS!E4*Assumptions!$C$19) | F12: =-(IS!F4*Assumptions!$C$19) | G12: =-(IS!G4*Assumptions!$C$19) | H12: =-(IS!H4*Assumptions!$C$19)
B13: Cash from Investing | D13: =D12 | E13: =E12 | F13: =F12 | G13: =G12 | H13: =H12
B15: Financing Activities
B16: Debt issuance / (repayment) | D16: =BS!D14-BS!C14 | E16: =BS!E14-BS!D14 | F16: =BS!F14-BS!E14 | G16: =BS!G14-BS!F14 | H16: =BS!H14-BS!G14
B17: Cash from Financing | D17: =D16 | E17: =E16 | F17: =F16 | G17: =G16 | H17: =H16
B19: Net change in cash | D19: =D9+D13+D17 | E19: =E9+E13+E17 | F19: =F9+F13+F17 | G19: =G9+G13+G17 | H19: =H9+H13+H17
B20: Beginning cash | D20: =BS!C4 | E20: =BS!D4 | F20: =BS!E4 | G20: =BS!F4 | H20: =BS!G4
B21: Ending cash | D21: =D19+D20 | E21: =E19+E20 | F21: =F19+F20 | G21: =G19+G20 | H21: =H19+H20

Sheet DCF
B1: Discounted Cash Flow
D2: 2026E | E2: 2027E | F2: 2028E | G2: 2029E | H2: 2030E
B4: EBIT | D4: =IS!D13 | E4: =IS!E13 | F4: =IS!F13 | G4: =IS!G13 | H4: =IS!H13
B5: Tax rate | D5: =Assumptions!$C$4 | E5: =Assumptions!$C$4 | F5: =Assumptions!$C$4 | G5: =Assumptions!$C$4 | H5: =Assumptions!$C$4
B6: NOPAT | D6: =D4*(1-D5) | E6: =E4*(1-E5) | F6: =F4*(1-F5) | G6: =G4*(1-G5) | H6: =H4*(1-H5)
B7: (+) D&A | D7: =IS!D12 | E7: =IS!E12 | F7: =IS!F12 | G7: =IS!G12 | H7: =IS!H12
B8: CapEx | D8: =CFS!D12 | E8: =CFS!E12 | F8: =CFS!F12 | G8: =CFS!G12 | H8: =CFS!H12
B9: Increase in NWC | D9: =(BS!D5+BS!D6-BS!D12)-(BS!C5+BS!C6-BS!C12) | E9: =(BS!E5+BS!E6-BS!E12)-(BS!D5+BS!D6-BS!D12) | F9: =(BS!F5+BS!F6-BS!F12)-(BS!E5+BS!E6-BS!E12) | G9: =(BS!G5+BS!G6-BS!G12)-(BS!F5+BS!F6-BS!F12) | H9: =(BS!H5+BS!H6-BS!H12)-(BS!G5+BS!G6-BS!G12)
B10: Unlevered Free Cash Flow | D10: =D6+D7+D8-D9 | E10: =E6+E7+E8-E9 | F10: =F6+F7+F8-F9 | G10: =G6+G7+G8-G9 | H10: =H6+H7+H8-H9
B12: Discount factor | D12: =1/(1+Assumptions!$C$6)^1 | E12: =1/(1+Assumptions!$C$6)^2 | F12: =1/(1+Assumptions!$C$6)^3 | G12: =1/(1+Assumptions!$C$6)^4 | H12: =1/(1+Assumptions!$C$6)^5
B13: Discounted FCF | D13: =D10*D12 | E13: =E10*E12 | F13: =F10*F12 | G13: =G10*G12 | H13: =H10*H12
B16: Terminal value | H16: =H10*(1+Assumptions!$C$7)/(Assumptions!$C$6-Assumptions!$C$7)
B17: Discounted terminal value | H17: =H16*H12
B20: Enterprise Value | C20: =SUM(D13:H13)+H17
B21: Less: Net Debt | C21: =-(BS!C14-BS!C4)
B22: Equity Value | C22: =C20+C21
B23: Value per Share | C23: =C22/Assumptions!$C$11
